{"nodes": [{"id": "test_health_state", "label": "Test Health State", "file_type": "code", "source_file": "tests/property/test_health_state.py", "source_location": null}, {"id": "TestHealthStateClassification", "label": "TestHealthStateClassification", "file_type": "code", "source_file": "tests/property/test_health_state.py", "source_location": 36}, {"id": "classify_health_state", "label": "classify_health_state", "file_type": "code", "source_file": "tests/property/test_health_state.py", "source_location": 15}], "edges": [{"source": "TestHealthStateClassification", "target": "test_health_state", "relation": "defines", "confidence": "EXTRACTED", "confidence_score": 1.0, "source_file": "tests/property/test_health_state.py", "weight": 1.0}, {"source": "classify_health_state", "target": "test_health_state", "relation": "defines", "confidence": "EXTRACTED", "confidence_score": 1.0, "source_file": "tests/property/test_health_state.py", "weight": 1.0}, {"source": "TestHealthStateClassification", "target": "classify_health_state", "relation": "calls", "confidence": "EXTRACTED", "confidence_score": 1.0, "source_file": "tests/property/test_health_state.py", "weight": 1.0}], "hyperedges": []}